{
  "theme": {
    "desk": "#E5D9CC",
    "paper": "#FFFDF8",
    "ink": "#2A2118",
    "muted": "#7A6E62",
    "line": "#C9BAA8",
    "tape": "#F2E4A0",
    "pin": "#D45B5B",
    "shadow": "rgba(42, 33, 24, 0.14)"
  },
  "openStudio": {
    "badge": "Community studio · open desks",
    "heading": "Every industry has a desk here",
    "subheading": "Students, coders, professionals, and educators — browse live sector snapshots from one shared studio floor. Pick a card. See who's building what.",
    "liveInside": 3261840,
    "refreshLabel": "Snapshots refresh every 45s",
    "defaultActive": "edtech",
    "autoCycle": true,
    "autoCycleMs": 8000,
    "personas": [
      "Students",
      "Coders",
      "Professionals",
      "Educators",
      "Career builders"
    ],
    "snapshots": [
      {
        "id": "edtech",
        "code": "EDU",
        "label": "EdTech",
        "cluster": "Technology & Digital",
        "learners": 518400,
        "mentors": 14200,
        "growth": 23,
        "color": "#5B5BD6",
        "tilt": -4,
        "audiences": ["Students", "Educators", "Career builders"],
        "caption": "Cohort labs running now",
        "insight": "Micro-credential stacks in instructional design and LMS engineering are the fastest enrollments this quarter.",
        "paths": ["Curriculum design", "LMS APIs", "Learning analytics"]
      },
      {
        "id": "saas",
        "code": "SAS",
        "label": "SaaS / Cloud",
        "cluster": "Technology & Digital",
        "learners": 442100,
        "mentors": 18600,
        "growth": 19,
        "color": "#0EA5E9",
        "tilt": 3,
        "audiences": ["Coders", "Professionals", "Career builders"],
        "caption": "Platform builders online",
        "insight": "Multi-tenant architecture and usage-based billing workshops draw engineers from every background.",
        "paths": ["Tenant isolation", "Billing engines", "Observability"]
      },
      {
        "id": "ai-ml",
        "code": "AI",
        "label": "AI & Machine Learning",
        "cluster": "Technology & Digital",
        "learners": 612800,
        "mentors": 22100,
        "growth": 31,
        "color": "#8B5CF6",
        "tilt": -2,
        "audiences": ["Students", "Coders", "Professionals"],
        "caption": "Model labs at peak",
        "insight": "RAG pipelines and fine-tuning sprints connect researchers with product teams shipping real features.",
        "paths": ["RAG systems", "Fine-tuning", "Eval harnesses"]
      },
      {
        "id": "cyber",
        "code": "SEC",
        "label": "CyberSecurity",
        "cluster": "Technology & Digital",
        "learners": 287600,
        "mentors": 9800,
        "growth": 17,
        "color": "#1E3A5F",
        "tilt": 5,
        "audiences": ["Coders", "Professionals"],
        "caption": "Threat rooms active",
        "insight": "Purple-team simulations and zero-trust design reviews are open to beginners and senior analysts alike.",
        "paths": ["Threat modeling", "Zero-trust", "Incident response"]
      },
      {
        "id": "fintech",
        "code": "FIN",
        "label": "FinTech",
        "cluster": "Finance & Banking",
        "learners": 334500,
        "mentors": 11200,
        "growth": 15,
        "color": "#059669",
        "tilt": -3,
        "audiences": ["Professionals", "Coders", "Career builders"],
        "caption": "Ledger desks open",
        "insight": "Payments API design and regulatory sandbox walkthroughs bridge banking veterans with new builders.",
        "paths": ["Payments APIs", "Compliance", "Risk engines"]
      },
      {
        "id": "health",
        "code": "HLT",
        "label": "HealthTech",
        "cluster": "Healthcare & Pharma",
        "learners": 198700,
        "mentors": 7600,
        "growth": 21,
        "color": "#E11D48",
        "tilt": 2,
        "audiences": ["Professionals", "Students", "Career builders"],
        "caption": "Clinical data circles",
        "insight": "FHIR integration and patient-data privacy studios attract clinicians learning to ship digital tools.",
        "paths": ["FHIR basics", "HIPAA design", "Clinical UX"]
      },
      {
        "id": "ecom",
        "code": "RTL",
        "label": "E-Commerce",
        "cluster": "Consumer & Retail",
        "learners": 376200,
        "mentors": 10400,
        "growth": 14,
        "color": "#F97316",
        "tilt": -5,
        "audiences": ["Professionals", "Career builders", "Students"],
        "caption": "Storefront sprints live",
        "insight": "Conversion optimization and catalog personalization projects are the top portfolio pieces for retail hires.",
        "paths": ["Catalog systems", "Personalization", "Checkout UX"]
      },
      {
        "id": "media",
        "code": "MED",
        "label": "OTT & Gaming",
        "cluster": "Media & Entertainment",
        "learners": 245900,
        "mentors": 8900,
        "growth": 18,
        "color": "#EC4899",
        "tilt": 4,
        "audiences": ["Coders", "Students", "Professionals"],
        "caption": "Stream ops running",
        "insight": "Live streaming infra and game netcode study groups share the same latency-obsessed community.",
        "paths": ["WebRTC", "CDN edge", "Live ops"]
      },
      {
        "id": "clean",
        "code": "CLN",
        "label": "CleanTech",
        "cluster": "Infrastructure & Energy",
        "learners": 124300,
        "mentors": 4200,
        "growth": 26,
        "color": "#16A34A",
        "tilt": -1,
        "audiences": ["Professionals", "Career builders", "Students"],
        "caption": "Grid forecast desks",
        "insight": "Carbon accounting and renewable forecasting notebooks connect energy analysts with software learners.",
        "paths": ["Carbon models", "Grid APIs", "Sensor fusion"]
      },
      {
        "id": "logistics",
        "code": "LOG",
        "label": "Supply Chain",
        "cluster": "Logistics & Mobility",
        "learners": 167800,
        "mentors": 5800,
        "growth": 12,
        "color": "#0891B2",
        "tilt": 3,
        "audiences": ["Professionals", "Career builders"],
        "caption": "Route rooms open",
        "insight": "Last-mile optimization and warehouse automation cohorts welcome ops managers learning to code.",
        "paths": ["Route optimization", "WMS APIs", "IoT telemetry"]
      },
      {
        "id": "gov",
        "code": "GOV",
        "label": "GovTech",
        "cluster": "Government & Social",
        "learners": 98400,
        "mentors": 3600,
        "growth": 20,
        "color": "#CA8A04",
        "tilt": -4,
        "audiences": ["Professionals", "Educators", "Career builders"],
        "caption": "Civic build hours",
        "insight": "Digital identity and open-data portal projects pair civil servants with volunteer developers worldwide.",
        "paths": ["Open data", "Digital ID", "Accessibility"]
      },
      {
        "id": "hr",
        "code": "HRT",
        "label": "HR Tech",
        "cluster": "Government & Social",
        "learners": 143600,
        "mentors": 5100,
        "growth": 13,
        "color": "#6366F1",
        "tilt": 2,
        "audiences": ["Professionals", "Educators"],
        "caption": "People analytics live",
        "insight": "Workforce planning and fairness-audit workshops draw HR leaders into data literacy paths.",
        "paths": ["People analytics", "Fairness audits", "HRIS APIs"]
      }
    ],
    "totals": [
      { "id": "learners", "value": "3.2M+", "label": "Active learners" },
      { "id": "desks", "value": "48", "label": "Sector desks" },
      { "id": "mentors", "value": "71K", "label": "Mentors on floor" },
      { "id": "countries", "value": "156", "label": "Countries present" }
    ],
    "actions": [
      { "id": "join", "label": "Claim a desk", "primary": true },
      { "id": "host", "label": "Host a session", "primary": false }
    ]
  }
}
